{"MMTC.NS": {"sector": "Industrials", "industry": "Conglomerates", "name": "MMTC LIMITED"}, "RVNL.NS": {"sector": "Industrials", "industry": "Engineering & Construction", "name": "RAIL VIKAS NIGAM LIMITED"}, "IRFC.NS": {"sector": "Financial Services", "industry": "Credit Services", "name": "INDIAN RAILWAY FIN CORP L"}, "HINDCOPPER.NS": {"sector": "Basic Materials", "industry": "Copper", "name": "HINDUSTAN COPPER LTD"}, "GMDCLTD.NS": {"sector": "Energy", "industry": "Thermal Coal", "name": "GUJARAT MINERAL DEV CORP"}, "RAILTEL.NS": {"sector": "Communication Services", "industry": "Telecom Services", "name": "RAILTEL CORP OF IND LTD"}, "KARURVYSYA.NS": {"sector": "Financial Services", "industry": "Banks - Regional", "name": "KARUR VYSYA BANK LTD"}, "NBCC.NS": {"sector": "Industrials", "industry": "Engineering & Construction", "name": "NBCC (INDIA) LIMITED"}, "TITAGARH.NS": {"sector": "Industrials", "industry": "Railroads", "name": "TITAGARH RAIL SYSTEMS LTD"}, "CRAFTSMAN.NS": {"sector": "Consumer Cyclical", "industry": "Auto Parts", "name": "CRAFTSMAN AUTOMATION LTD"}, "IRCON.NS": {"sector": "Industrials", "industry": "Engineering & Construction", "name": "IRCON INTERNATIONAL LTD"}, "IRCTC.NS": {"sector": "Consumer Cyclical", "industry": "Travel Services", "name": "INDIAN RAIL TOUR CORP LTD"}, "RITES.NS": {"sector": "Industrials", "industry": "Engineering & Construction", "name": "RITES LIMITED"}, "THELEELA.NS": {"sector": "Consumer Cyclical", "industry": "Lodging", "name": "LEELA PALACES HOTEL LTD"}, "ASTERDM.NS": {"sector": "Healthcare", "industry": "Medical Care Facilities", "name": "ASTER DM HEALTHCARE LTD."}, "NATIONALUM.NS": {"sector": "Basic Materials", "industry": "Aluminum", "name": "NATIONAL ALUMINIUM CO LTD"}, "SCI.NS": {"sector": "Industrials", "industry": "Marine Shipping", "name": "SHIPPING CORP OF INDIA LT"}, "CASTROLIND.NS": {"sector": "Energy", "industry": "Oil & Gas Refining & Marketing", "name": "CASTROL INDIA LIMITED"}, "HUDCO.NS": {"sector": "Financial Services", "industry": "Credit Services", "name": "HSG & URBAN DEV CORPN LTD"}, "DALBHARAT.NS": {"sector": "Basic Materials", "industry": "Building Materials", "name": "DALMIA BHARAT LIMITED"}, "ASAHIINDIA.NS": {"sector": "Consumer Cyclical", "industry": "Auto Parts", "name": "ASAHI INDIA GLASS LIMITED"}, "NIACL.NS": {"sector": "Financial Services", "industry": "Insurance - Diversified", "name": "THE NEW INDIA ASSU CO LTD"}, "OLAELEC.NS": {"sector": "Consumer Cyclical", "industry": "Auto Manufacturers", "name": "OLA ELECTRIC MOBILITY LTD"}, "PTCIL.NS": {"sector": "Industrials", "industry": "Metal Fabrication", "name": "PTC INDUSTRIES LIMITED"}, "TITAN.NS": {"sector": "Consumer Cyclical", "industry": "Luxury Goods", "name": "TITAN COMPANY LIMITED"}, "SONATSOFTW.NS": {"sector": "Technology", "industry": "Information Technology Services", "name": "SONATA SOFTWARE LTD"}, "CONCOR.NS": {"sector": "Industrials", "industry": "Railroads", "name": "CONTAINER CORP OF IND LTD"}, "GILLETTE.NS": {"sector": "Consumer Defensive", "industry": "Household & Personal Products", "name": "GILLETTE INDIA LTD"}, "MCX.NS": {"sector": "Financial Services", "industry": "Financial Data & Stock Exchanges", "name": "MULTI COMMODITY EXCHANGE"}, "ENGINERSIN.NS": {"sector": "Industrials", "industry": "Engineering & Construction", "name": "ENGINEERS INDIA LTD"}, "IGIL.NS": {"sector": "Basic Materials", "industry": "Other Precious Metals & Mining", "name": "INTERNATIO GEMM INS (I) L"}, "LINDEINDIA.NS": {"sector": "Basic Materials", "industry": "Specialty Chemicals", "name": "LINDE INDIA LIMITED"}, "IREDA.NS": {"sector": "Financial Services", "industry": "Credit Services", "name": "INDIAN RENEWABLE ENERGY"}, "HINDZINC.NS": {"sector": "Basic Materials", "industry": "Other Industrial Metals & Mining", "name": "HINDUSTAN ZINC LIMITED"}, "GRAPHITE.NS": {"sector": "Industrials", "industry": "Electrical Equipment & Parts", "name": "GRAPHITE INDIA LTD"}, "GRSE.NS": {"sector": "Industrials", "industry": "Aerospace & Defense", "name": "GARDEN REACH SHIP&ENG LTD"}, "ADANIENSOL.NS": {"sector": "Utilities", "industry": "Utilities - Independent Power Producers", "name": "ADANI ENERGY SOLUTION LTD"}, "HBLENGINE.NS": {"sector": "Industrials", "industry": "Electrical Equipment & Parts", "name": "HBL ENGINEERING LTD"}, "HEG.NS": {"sector": "Industrials", "industry": "Electrical Equipment & Parts", "name": "HEG LTD"}, "APLAPOLLO.NS": {"sector": "Basic Materials", "industry": "Steel", "name": "APL APOLLO TUBES LTD"}, "INDIACEM.NS": {"sector": "Basic Materials", "industry": "Building Materials", "name": "THE INDIA CEMENTS LIMITED"}, "ONESOURCE.NS": {"sector": "Healthcare", "industry": "Biotechnology", "name": "ONESOURCE SPECL PHARMA L"}, "ITCHOTELS.NS": {"sector": "Consumer Cyclical", "industry": "Resorts & Casinos", "name": "ITC HOTELS LIMITED"}, "FACT.NS": {"sector": "Basic Materials", "industry": "Agricultural Inputs", "name": "FACT LTD"}, "IPCALAB.NS": {"sector": "Healthcare", "industry": "Drug Manufacturers - Specialty & Generic", "name": "IPCA LABORATORIES LTD"}, "TORNTPOWER.NS": {"sector": "Utilities", "industry": "Utilities - Independent Power Producers", "name": "TORRENT POWER LTD"}, "DEEPAKNTR.NS": {"sector": "Basic Materials", "industry": "Chemicals", "name": "DEEPAK NITRITE LTD"}, "ABBOTINDIA.NS": {"sector": "Healthcare", "industry": "Drug Manufacturers - Specialty & Generic", "name": "ABBOTT INDIA LIMITED"}, "NMDC.NS": {"sector": "Basic Materials", "industry": "Steel", "name": "NMDC LTD."}, "JWL.NS": {"sector": "Industrials", "industry": "Railroads", "name": "JUPITER WAGONS LIMITED"}, "SHREECEM.NS": {"sector": "Basic Materials", "industry": "Building Materials", "name": "SHREE CEMENT LIMITED"}, "VBL.NS": {"sector": "Consumer Defensive", "industry": "Beverages - Non-Alcoholic", "name": "VARUN BEVERAGES LIMITED"}, "METROPOLIS.NS": {"sector": "Healthcare", "industry": "Diagnostics & Research", "name": "METROPOLIS HEALTHCARE LTD"}, "MARICO.NS": {"sector": "Consumer Defensive", "industry": "Household & Personal Products", "name": "MARICO LIMITED"}, "BIKAJI.NS": {"sector": "Consumer Defensive", "industry": "Packaged Foods", "name": "BIKAJI FOODS INTERN LTD"}, "AMBUJACEM.NS": {"sector": "Basic Materials", "industry": "Building Materials", "name": "AMBUJA CEMENTS LTD"}, "ENRIN.NS": {"sector": "Utilities", "industry": "Utilities - Renewable", "name": "SIEMENS ENERGY INDIA LTD"}, "EIHOTEL.NS": {"sector": "Consumer Cyclical", "industry": "Lodging", "name": "EIH LIMITED"}, "ATGL.NS": {"sector": "Utilities", "industry": "Utilities - Regulated Gas", "name": "ADANI TOTAL GAS LIMITED"}, "IDFCFIRSTB.NS": {"sector": "Financial Services", "industry": "Banks - Regional", "name": "IDFC FIRST BANK LIMITED"}, "SCHAEFFLER.NS": {"sector": "Consumer Cyclical", "industry": "Auto Parts", "name": "SCHAEFFLER INDIA LIMITED"}, "HINDALCO.NS": {"sector": "Basic Materials", "industry": "Aluminum", "name": "HINDALCO  INDUSTRIES  LTD"}, "EMCURE.NS": {"sector": "Healthcare", "industry": "Drug Manufacturers - Specialty & Generic", "name": "EMCURE PHARMACEUTICALS L"}, "BEML.NS": {"sector": "Industrials", "industry": "Conglomerates", "name": "BEML LIMITED"}, "M&MFIN.NS": {"sector": "Financial Services", "industry": "Credit Services", "name": "M&M FIN. SERVICES LTD"}, "POONAWALLA.NS": {"sector": "Financial Services", "industry": "Credit Services", "name": "POONAWALLA FINCORP LTD"}, "NUVOCO.NS": {"sector": "Basic Materials", "industry": "Building Materials", "name": "NUVOCO VISTAS CORP LTD"}, "BHEL.NS": {"sector": "Industrials", "industry": "Specialty Industrial Machinery", "name": "BHEL"}, "SUMICHEM.NS": {"sector": "Basic Materials", "industry": "Agricultural Inputs", "name": "SUMITOMO CHEM INDIA LTD"}, "NESTLEIND.NS": {"sector": "Consumer Defensive", "industry": "Packaged Foods", "name": "NESTLE INDIA LIMITED"}, "SAGILITY.NS": {"sector": "Healthcare", "industry": "Health Information Services", "name": "SAGILITY LIMITED"}, "AKUMS.NS": {"sector": "Healthcare", "industry": "Drug Manufacturers - Specialty & Generic", "name": "AKUMS DRUGS AND PHARMA L"}, "CHOICEIN.NS": {"sector": "Financial Services", "industry": "Capital Markets", "name": "CHOICE INTERNATIONAL LTD"}, "OBEROIRLTY.NS": {"sector": "Real Estate", "industry": "Real Estate - Development", "name": "OBEROI REALTY LIMITED"}, "IDBI.NS": {"sector": "Financial Services", "industry": "Banks - Regional", "name": "IDBI BANK LIMITED"}, "NEULANDLAB.NS": {"sector": "Healthcare", "industry": "Drug Manufacturers - Specialty & Generic", "name": "NEULAND LAB LTD."}, "PFC.NS": {"sector": "Financial Services", "industry": "Credit Services", "name": "POWER FIN CORP LTD."}, "BHARTIHEXA.NS": {"sector": "Communication Services", "industry": "Telecom Services", "name": "BHARTI HEXACOM LIMITED"}, "PIDILITIND.NS": {"sector": "Basic Materials", "industry": "Specialty Chemicals", "name": "PIDILITE INDUSTRIES LTD"}, "RHIM.NS": {"sector": "Industrials", "industry": "Metal Fabrication", "name": "RHI MAGNESITA INDIA LTD"}, "KFINTECH.NS": {"sector": "Technology", "industry": "Software - Application", "name": "KFIN TECHNOLOGIES LIMITED"}, "RECLTD.NS": {"sector": "Financial Services", "industry": "Credit Services", "name": "REC LIMITED"}, "KALYANKJIL.NS": {"sector": "Consumer Cyclical", "industry": "Luxury Goods", "name": "KALYAN JEWELLERS IND LTD"}, "AFCONS.NS": {"sector": "Industrials", "industry": "Engineering & Construction", "name": "AFCONS INFRASTRUCTURE LTD"}, "EIDPARRY.NS": {"sector": "Basic Materials", "industry": "Agricultural Inputs", "name": "EID PARRY INDIA LTD"}, "KIRLOSENG.NS": {"sector": "Industrials", "industry": "Specialty Industrial Machinery", "name": "KIRLOSKAR OIL ENG LTD"}, "GODREJCP.NS": {"sector": "Consumer Defensive", "industry": "Household & Personal Products", "name": "GODREJ CONSUMER PRODUCTS"}, "NYKAA.NS": {"sector": "Consumer Cyclical", "industry": "Internet Retail", "name": "FSN E COMMERCE VENTURES"}, "GLAND.NS": {"sector": "Healthcare", "industry": "Drug Manufacturers - Specialty & Generic", "name": "GLAND PHARMA LIMITED"}, "BAYERCROP.NS": {"sector": "Basic Materials", "industry": "Agricultural Inputs", "name": "BAYER CROPSCIENCE LTD"}, "FINPIPE.NS": {"sector": "Industrials", "industry": "Building Products & Equipment", "name": "FINOLEX INDUSTRIES LTD"}, "WOCKPHARMA.NS": {"sector": "Healthcare", "industry": "Drug Manufacturers - Specialty & Generic", "name": "WOCKHARDT LIMITED"}, "SWANCORP.NS": {"sector": "Industrials", "industry": "Conglomerates", "name": "SWAN CORP LIMITED"}, "RCF.NS": {"sector": "Basic Materials", "industry": "Agricultural Inputs", "name": "RASHTRIYA CHEMICALS & FER"}, "JUBLPHARMA.NS": {"sector": "Healthcare", "industry": "Drug Manufacturers - Specialty & Generic", "name": "JUBILANT PHARMOVA LTD"}, "FORCEMOT.NS": {"sector": "Consumer Cyclical", "industry": "Auto Manufacturers", "name": "FORCE MOTORS LIMITED"}, "GUJGASLTD.NS": {"sector": "Utilities", "industry": "Utilities - Regulated Gas", "name": "GUJARAT GAS LIMITED"}, "NTPC.NS": {"sector": "Utilities", "industry": "Utilities - Regulated Electric", "name": "NTPC LTD"}, "GODFRYPHLP.NS": {"sector": "Consumer Defensive", "industry": "Tobacco", "name": "GODFREY PHILLIPS INDIA LT"}, "MGL.NS": {"sector": "Utilities", "industry": "Utilities - Regulated Gas", "name": "MAHANAGAR GAS LTD."}, "CIPLA.NS": {"sector": "Healthcare", "industry": "Drug Manufacturers - Specialty & Generic", "name": "CIPLA LTD"}, "NHPC.NS": {"sector": "Utilities", "industry": "Utilities - Renewable", "name": "NHPC LTD"}, "TATACOMM.NS": {"sector": "Communication Services", "industry": "Telecom Services", "name": "TATA COMMUNICATIONS LTD"}, "VEDL.NS": {"sector": "Basic Materials", "industry": "Other Industrial Metals & Mining", "name": "VEDANTA LIMITED"}, "HYUNDAI.NS": {"sector": "Consumer Cyclical", "industry": "Auto Manufacturers", "name": "HYUNDAI MOTOR INDIA LTD"}, "THERMAX.NS": {"sector": "Industrials", "industry": "Conglomerates", "name": "THERMAX LTD"}, "GRANULES.NS": {"sector": "Healthcare", "industry": "Drug Manufacturers - Specialty & Generic", "name": "GRANULES INDIA LIMITED"}, "DELHIVERY.NS": {"sector": "Industrials", "industry": "Integrated Freight & Logistics", "name": "DELHIVERY LIMITED"}, "UNITDSPR.NS": {"sector": "Consumer Defensive", "industry": "Beverages - Wineries & Distilleries", "name": "UNITED SPIRITS LIMITED"}, "SAREGAMA.NS": {"sector": "Communication Services", "industry": "Entertainment", "name": "SAREGAMA INDIA LIMITED"}, "VIJAYA.NS": {"sector": "Healthcare", "industry": "Diagnostics & Research", "name": "VIJAYA DIAGNOSTIC CEN LTD"}, "CGCL.NS": {"sector": "Financial Services", "industry": "Credit Services", "name": "CAPRI GLOBAL CAPITAL LTD"}, "KPRMILL.NS": {"sector": "Consumer Cyclical", "industry": "Textile Manufacturing", "name": "KPR MILL LTD."}, "PIIND.NS": {"sector": "Basic Materials", "industry": "Agricultural Inputs", "name": "PI INDUSTRIES LTD"}, "VTL.NS": {"sector": "Consumer Cyclical", "industry": "Textile Manufacturing", "name": "VARDHMAN TEXTILES LIMITED"}, "INDHOTEL.NS": {"sector": "Consumer Cyclical", "industry": "Lodging", "name": "THE INDIAN HOTELS CO. LTD"}, "MAZDOCK.NS": {"sector": "Industrials", "industry": "Aerospace & Defense", "name": "MAZAGON DOCK SHIPBUIL LTD"}, "ADANIENT.NS": {"sector": "Energy", "industry": "Thermal Coal", "name": "ADANI ENTERPRISES LIMITED"}, "SAIL.NS": {"sector": "Basic Materials", "industry": "Steel", "name": "STEEL AUTHORITY OF INDIA"}, "ONGC.NS": {"sector": "Energy", "industry": "Oil & Gas Integrated", "name": "OIL AND NATURAL GAS CORP."}, "NSLNISP.NS": {"sector": "Basic Materials", "industry": "Steel", "name": "NMDC STEEL LIMITED"}, "COCHINSHIP.NS": {"sector": "Industrials", "industry": "Aerospace & Defense", "name": "COCHIN SHIPYARD LIMITED"}, "COHANCE.NS": {"sector": "Healthcare", "industry": "Drug Manufacturers - Specialty & Generic", "name": "COHANCE LIFESCIENCES LTD"}, "DATAPATTNS.NS": {"sector": "Industrials", "industry": "Aerospace & Defense", "name": "DATA PATTERNS INDIA LTD"}, "BLUEDART.NS": {"sector": "Industrials", "industry": "Integrated Freight & Logistics", "name": "BLUE DART EXPRESS LTD"}, "MAHSCOOTER.NS": {"sector": "Financial Services", "industry": "Asset Management", "name": "MAHARASHTRA SCOOTERS LTD"}, "GSPL.NS": {"sector": "Utilities", "industry": "Utilities - Regulated Gas", "name": "GUJARAT STATE PETRO LTD"}, "GODREJIND.NS": {"sector": "Industrials", "industry": "Conglomerates", "name": "GODREJ INDUSTRIES LTD"}, "SYRMA.NS": {"sector": "Technology", "industry": "Electronic Components", "name": "SYRMA SGS TECHNOLOGY LTD"}, "SYNGENE.NS": {"sector": "Healthcare", "industry": "Diagnostics & Research", "name": "SYNGENE INTERNATIONAL LTD"}, "JSWSTEEL.NS": {"sector": "Basic Materials", "industry": "Steel", "name": "JSW STEEL LIMITED"}, "JYOTHYLAB.NS": {"sector": "Consumer Defensive", "industry": "Household & Personal Products", "name": "JYOTHY LABS LIMITED"}, "PFIZER.NS": {"sector": "Healthcare", "industry": "Drug Manufacturers - General", "name": "PFIZER LTD"}, "IFCI.NS": {"sector": "Financial Services", "industry": "Credit Services", "name": "IFCI LTD"}, "ATUL.NS": {"sector": "Basic Materials", "industry": "Specialty Chemicals", "name": "ATUL LTD"}, "HINDUNILVR.NS": {"sector": "Consumer Defensive", "industry": "Household & Personal Products", "name": "HINDUSTAN UNILEVER LTD."}, "TMPV.NS": {"sector": "Consumer Cyclical", "industry": "Auto Manufacturers", "name": "TATA MOTORS PASS VEH LTD"}, "EICHERMOT.NS": {"sector": "Consumer Cyclical", "industry": "Auto Manufacturers", "name": "EICHER MOTORS LTD"}, "SIEMENS.NS": {"sector": "Industrials", "industry": "Specialty Industrial Machinery", "name": "SIEMENS LTD"}, "KAJARIACER.NS": {"sector": "Industrials", "industry": "Building Products & Equipment", "name": "KAJARIA CERAMICS LTD"}, "GPIL.NS": {"sector": "Basic Materials", "industry": "Steel", "name": "GODAWARI POW & ISP LTD"}, "DEEPAKFERT.NS": {"sector": "Basic Materials", "industry": "Chemicals", "name": "DEEPAK FERTILIZERS & PETR"}, "AXISBANK.NS": {"sector": "Financial Services", "industry": "Banks - Regional", "name": "AXIS BANK LIMITED"}, "CANBK.NS": {"sector": "Financial Services", "industry": "Banks - Regional", "name": "CANARA BANK"}, "SUNDARMFIN.NS": {"sector": "Financial Services", "industry": "Credit Services", "name": "SUNDARAM FINANCE LTD"}, "AFFLE.NS": {"sector": "Communication Services", "industry": "Advertising Agencies", "name": "AFFLE 3I LIMITED"}, "VMM.NS": {"sector": "Consumer Cyclical", "industry": "Department Stores", "name": "VISHAL MEGA MART LIMITED"}, "DOMS.NS": {"sector": "Industrials", "industry": "Business Equipment & Supplies", "name": "DOMS INDUSTRIES LIMITED"}, "LICHSGFIN.NS": {"sector": "Financial Services", "industry": "Mortgage Finance", "name": "LIC HOUSING FINANCE LTD"}, "RAMCOCEM.NS": {"sector": "Basic Materials", "industry": "Building Materials", "name": "THE RAMCO CEMENTS LIMITED"}, "PETRONET.NS": {"sector": "Energy", "industry": "Oil & Gas Refining & Marketing", "name": "PETRONET LNG LIMITED"}, "SOBHA.NS": {"sector": "Real Estate", "industry": "Real Estate - Development", "name": "SOBHA LIMITED"}, "CARBORUNIV.NS": {"sector": "Industrials", "industry": "Conglomerates", "name": "CARBORUNDUM UNIVERSAL LTD"}, "RELIANCE.NS": {"sector": "Energy", "industry": "Oil & Gas Refining & Marketing", "name": "RELIANCE INDUSTRIES LTD"}, "ULTRACEMCO.NS": {"sector": "Basic Materials", "industry": "Building Materials", "name": "ULTRATECH CEMENT LIMITED"}, "CHOLAFIN.NS": {"sector": "Financial Services", "industry": "Credit Services", "name": "CHOLAMANDALAM IN & FIN CO"}, "DRREDDY.NS": {"sector": "Healthcare", "industry": "Drug Manufacturers - Specialty & Generic", "name": "DR. REDDY S LABORATORIES"}, "MAHSEAMLES.NS": {"sector": "Basic Materials", "industry": "Steel", "name": "MAHARASHTRA SEAMLESS LTD"}, "GRAVITA.NS": {"sector": "Industrials", "industry": "Metal Fabrication", "name": "GRAVITA INDIA LIMITED"}, "ADANIGREEN.NS": {"sector": "Utilities", "industry": "Utilities - Renewable", "name": "ADANI GREEN ENERGY LTD"}, "SUZLON.NS": {"sector": "Industrials", "industry": "Specialty Industrial Machinery", "name": "SUZLON ENERGY LIMITED"}, "GAIL.NS": {"sector": "Utilities", "industry": "Utilities - Regulated Gas", "name": "GAIL (INDIA) LTD"}, "IOB.NS": {"sector": "Financial Services", "industry": "Banks - Regional", "name": "INDIAN OVERSEAS BANK"}, "BRIGADE.NS": {"sector": "Real Estate", "industry": "Real Estate - Development", "name": "BRIGADE ENTER. LTD"}, "ABCAPITAL.NS": {"sector": "Financial Services", "industry": "Financial Conglomerates", "name": "ADITYA BIRLA CAPITAL LTD."}, "VENTIVE.NS": {"sector": "Consumer Cyclical", "industry": "Lodging", "name": "VENTIVE HOSPITALITY LTD"}, "3MINDIA.NS": {"sector": "Industrials", "industry": "Conglomerates", "name": "3M INDIA LIMITED"}, "LAURUSLABS.NS": {"sector": "Healthcare", "industry": "Drug Manufacturers - Specialty & Generic", "name": "LAURUS LABS LIMITED"}, "AWL.NS": {"sector": "Consumer Defensive", "industry": "Packaged Foods", "name": "AWL AGRI BUSINESS LIMITED"}, "BDL.NS": {"sector": "Industrials", "industry": "Aerospace & Defense", "name": "BHARAT DYNAMICS LIMITED"}, "TIINDIA.NS": {"sector": "Industrials", "industry": "Conglomerates", "name": "TUBE INVEST OF INDIA LTD"}, "SRF.NS": {"sector": "Industrials", "industry": "Conglomerates", "name": "SRF LTD"}, "BPCL.NS": {"sector": "Energy", "industry": "Oil & Gas Refining & Marketing", "name": "BHARAT PETROLEUM CORP  LT"}, "DLF.NS": {"sector": "Real Estate", "industry": "Real Estate - Development", "name": "DLF LIMITED"}, "ELECON.NS": {"sector": "Industrials", "industry": "Specialty Industrial Machinery", "name": "ELECON ENG. CO. LTD"}, "NLCINDIA.NS": {"sector": "Utilities", "industry": "Utilities - Regulated Electric", "name": "NLC INDIA LIMITED"}, "AADHARHFC.NS": {"sector": "Financial Services", "industry": "Mortgage Finance", "name": "AADHAR HOUSING FINANCE L"}, "TORNTPHARM.NS": {"sector": "Healthcare", "industry": "Drug Manufacturers - Specialty & Generic", "name": "TORRENT PHARMACEUTICALS L"}, "BAJAJHFL.NS": {"sector": "Financial Services", "industry": "Mortgage Finance", "name": "BAJAJ HOUSING FINANCE LTD"}, "BATAINDIA.NS": {"sector": "Consumer Cyclical", "industry": "Footwear & Accessories", "name": "BATA INDIA LTD"}, "AUBANK.NS": {"sector": "Financial Services", "industry": "Banks - Regional", "name": "AU SMALL FINANCE BANK LTD"}, "BANKINDIA.NS": {"sector": "Financial Services", "industry": "Banks - Regional", "name": "BANK OF INDIA"}, "HEXT.NS": {"sector": "Technology", "industry": "Information Technology Services", "name": "HEXAWARE TECHNOLOGIES LTD"}, "INDUSINDBK.NS": {"sector": "Financial Services", "industry": "Banks - Regional", "name": "INDUSIND BANK LIMITED"}, "COALINDIA.NS": {"sector": "Energy", "industry": "Thermal Coal", "name": "COAL INDIA LTD"}, "LALPATHLAB.NS": {"sector": "Healthcare", "industry": "Diagnostics & Research", "name": "DR. LAL PATH LABS LTD."}, "MANKIND.NS": {"sector": "Healthcare", "industry": "Drug Manufacturers - Specialty & Generic", "name": "MANKIND PHARMA LIMITED"}, "UBL.NS": {"sector": "Consumer Defensive", "industry": "Beverages - Brewers", "name": "UNITED BREWERIES LTD"}, "JUBLINGREA.NS": {"sector": "Basic Materials", "industry": "Specialty Chemicals", "name": "JUBILANT INGREVIA LIMITED"}, "SOLARINDS.NS": {"sector": "Basic Materials", "industry": "Specialty Chemicals", "name": "SOLAR INDUSTRIES (I) LTD"}, "MUTHOOTFIN.NS": {"sector": "Financial Services", "industry": "Credit Services", "name": "MUTHOOT FINANCE LIMITED"}, "ZFCVINDIA.NS": {"sector": "Consumer Cyclical", "industry": "Auto Parts", "name": "ZF COM VE CTR SYS IND LTD"}, "POWERINDIA.NS": {"sector": "Industrials", "industry": "Electrical Equipment & Parts", "name": "HITACHI ENERGY INDIA LTD"}, "LT.NS": {"sector": "Industrials", "industry": "Engineering & Construction", "name": "LARSEN & TOUBRO LTD."}, "TRIVENI.NS": {"sector": "Consumer Defensive", "industry": "Confectioners", "name": "TRIVENI ENGG. & INDS. LTD"}, "UPL.NS": {"sector": "Basic Materials", "industry": "Agricultural Inputs", "name": "UPL LIMITED"}, "ABLBL.NS": {"sector": "Consumer Cyclical", "industry": "Apparel Retail", "name": "ADITYA BIRLA LIFES BRAN L"}, "TATAPOWER.NS": {"sector": "Utilities", "industry": "Utilities - Independent Power Producers", "name": "TATA POWER CO LTD"}, "JBCHEPHARM.NS": {"sector": "Healthcare", "industry": "Drug Manufacturers - Specialty & Generic", "name": "J B CHEMICALS AND PHARMA"}, "PATANJALI.NS": {"sector": "Consumer Defensive", "industry": "Packaged Foods", "name": "PATANJALI FOODS LIMITED"}, "KOTAKBANK.NS": {"sector": "Financial Services", "industry": "Banks - Regional", "name": "KOTAK MAHINDRA BANK LTD"}, "RADICO.NS": {"sector": "Consumer Defensive", "industry": "Beverages - Wineries & Distilleries", "name": "RADICO KHAITAN LTD"}, "PGEL.NS": {"sector": "Technology", "industry": "Electronic Components", "name": "PG ELECTROPLAST LTD"}, "HSCL.NS": {"sector": "Basic Materials", "industry": "Specialty Chemicals", "name": "HIMADRI SPECIALITY CHEM L"}, "NAUKRI.NS": {"sector": "Communication Services", "industry": "Internet Content & Information", "name": "INFO EDGE (I) LTD"}, "BALKRISIND.NS": {"sector": "Consumer Cyclical", "industry": "Auto Parts", "name": "BALKRISHNA IND. LTD"}, "GODREJAGRO.NS": {"sector": "Consumer Defensive", "industry": "Packaged Foods", "name": "GODREJ AGROVET LIMITED"}, "GLENMARK.NS": {"sector": "Healthcare", "industry": "Drug Manufacturers - Specialty & Generic", "name": "GLENMARK PHARMACEUTICALS"}, "ITI.NS": {"sector": "Technology", "industry": "Communication Equipment", "name": "ITI LTD"}, "GICRE.NS": {"sector": "Financial Services", "industry": "Insurance - Reinsurance", "name": "GENERAL INS CORP OF INDIA"}, "PHOENIXLTD.NS": {"sector": "Real Estate", "industry": "Real Estate - Diversified", "name": "THE PHOENIX MILLS LTD"}, "IGL.NS": {"sector": "Utilities", "industry": "Utilities - Regulated Gas", "name": "INDRAPRASTHA GAS LTD"}, "CHAMBLFERT.NS": {"sector": "Basic Materials", "industry": "Agricultural Inputs", "name": "CHAMBAL FERTILIZERS LTD"}, "BRITANNIA.NS": {"sector": "Consumer Defensive", "industry": "Packaged Foods", "name": "BRITANNIA INDUSTRIES LTD"}, "CROMPTON.NS": {"sector": "Consumer Cyclical", "industry": "Furnishings, Fixtures & Appliances", "name": "CROMPT GREA CON ELEC LTD"}, "APOLLOHOSP.NS": {"sector": "Healthcare", "industry": "Medical Care Facilities", "name": "APOLLO HOSPITALS ENTER. L"}, "FEDERALBNK.NS": {"sector": "Financial Services", "industry": "Banks - Regional", "name": "FEDERAL BANK LTD"}, "KIMS.NS": {"sector": "Healthcare", "industry": "Medical Care Facilities", "name": "KRISHNA INST OF MED SCI L"}, "HAL.NS": {"sector": "Industrials", "industry": "Aerospace & Defense", "name": "HINDUSTAN AERONAUTICS LTD"}, "FORTIS.NS": {"sector": "Healthcare", "industry": "Medical Care Facilities", "name": "FORTIS HEALTHCARE LTD"}, "BSOFT.NS": {"sector": "Technology", "industry": "Information Technology Services", "name": "BIRLASOFT LIMITED"}, "ICICIPRULI.NS": {"sector": "Financial Services", "industry": "Insurance - Life", "name": "ICICI PRU LIFE INS CO LTD"}, "AEGISVOPAK.NS": {"sector": "Energy", "industry": "Oil & Gas Equipment & Services", "name": "AEGIS VOPAK TERMINALS LTD"}, "GRASIM.NS": {"sector": "Basic Materials", "industry": "Building Materials", "name": "GRASIM INDUSTRIES LTD"}, "TBOTEK.NS": {"sector": "Consumer Cyclical", "industry": "Travel Services", "name": "TBO TEK LIMITED"}, "TRENT.NS": {"sector": "Consumer Cyclical", "industry": "Apparel Retail", "name": "TRENT LTD"}, "ACC.NS": {"sector": "Basic Materials", "industry": "Building Materials", "name": "ACC LIMITED"}, "SONACOMS.NS": {"sector": "Consumer Cyclical", "industry": "Auto Parts", "name": "SONA BLW PRECISION FRGS L"}, "TATACHEM.NS": {"sector": "Basic Materials", "industry": "Chemicals", "name": "TATA CHEMICALS LTD"}, "ANANDRATHI.NS": {"sector": "Financial Services", "industry": "Asset Management", "name": "ANAND RATHI WEALTH LTD"}, "SBIN.NS": {"sector": "Financial Services", "industry": "Banks - Regional", "name": "STATE BANK OF INDIA"}, "INDIANB.NS": {"sector": "Financial Services", "industry": "Banks - Regional", "name": "INDIAN BANK"}, "PAGEIND.NS": {"sector": "Consumer Cyclical", "industry": "Apparel Manufacturing", "name": "PAGE INDUSTRIES LTD"}, "AUROPHARMA.NS": {"sector": "Healthcare", "industry": "Drug Manufacturers - Specialty & Generic", "name": "AUROBINDO PHARMA LTD"}, "JINDALSAW.NS": {"sector": "Basic Materials", "industry": "Steel", "name": "JINDAL SAW LIMITED"}, "M&M.NS": {"sector": "Consumer Cyclical", "industry": "Auto Manufacturers", "name": "MAHINDRA & MAHINDRA LTD"}, "DMART.NS": {"sector": "Consumer Defensive", "industry": "Discount Stores", "name": "AVENUE SUPERMARTS LIMITED"}, "HONAUT.NS": {"sector": "Industrials", "industry": "Electrical Equipment & Parts", "name": "HONEYWELL AUTOMATION IND"}, "FLUOROCHEM.NS": {"sector": "Basic Materials", "industry": "Specialty Chemicals", "name": "GUJARAT FLUOROCHEM LTD"}, "LUPIN.NS": {"sector": "Healthcare", "industry": "Drug Manufacturers - Specialty & Generic", "name": "LUPIN LIMITED"}, "SBICARD.NS": {"sector": "Financial Services", "industry": "Credit Services", "name": "SBI CARDS & PAY SER LTD"}, "GODREJPROP.NS": {"sector": "Real Estate", "industry": "Real Estate - Development", "name": "GODREJ PROPERTIES LTD"}, "OFSS.NS": {"sector": "Technology", "industry": "Software - Infrastructure", "name": "ORACLE FIN SERV SOFT LTD."}, "CENTRALBK.NS": {"sector": "Financial Services", "industry": "Banks - Regional", "name": "CENTRAL BANK OF INDIA"}, "INDIGO.NS": {"sector": "Industrials", "industry": "Airlines", "name": "INTERGLOBE AVIATION LTD"}, "SIGNATURE.NS": {"sector": "Real Estate", "industry": "Real Estate - Development", "name": "SIGNATUREGLOBAL INDIA LTD"}, "CYIENT.NS": {"sector": "Industrials", "industry": "Conglomerates", "name": "CYIENT LIMITED"}, "ICICIGI.NS": {"sector": "Financial Services", "industry": "Insurance - Diversified", "name": "ICICI LOMBARD GIC LIMITED"}, "DEVYANI.NS": {"sector": "Consumer Cyclical", "industry": "Restaurants", "name": "DEVYANI INTERNATIONAL LTD"}, "MANAPPURAM.NS": {"sector": "Financial Services", "industry": "Credit Services", "name": "MANAPPURAM FINANCE LTD"}, "HDFCAMC.NS": {"sector": "Financial Services", "industry": "Asset Management", "name": "HDFC AMC LIMITED"}, "POLICYBZR.NS": {"sector": "Financial Services", "industry": "Insurance Brokers", "name": "PB FINTECH LIMITED"}, "EMAMILTD.NS": {"sector": "Consumer Defensive", "industry": "Household & Personal Products", "name": "EMAMI LIMITED"}, "IRB.NS": {"sector": "Industrials", "industry": "Infrastructure Operations", "name": "IRB INFRA DEV LTD."}, "APTUS.NS": {"sector": "Financial Services", "industry": "Mortgage Finance", "name": "APTUS VALUE HSG FIN I LTD"}, "BASF.NS": {"sector": "Basic Materials", "industry": "Specialty Chemicals", "name": "BASF INDIA LTD"}, "INOXWIND.NS": {"sector": "Industrials", "industry": "Specialty Industrial Machinery", "name": "INOX WIND LIMITED"}, "INFY.NS": {"sector": "Technology", "industry": "Information Technology Services", "name": "INFOSYS LIMITED"}, "SBILIFE.NS": {"sector": "Financial Services", "industry": "Insurance - Life", "name": "SBI LIFE INSURANCE CO LTD"}, "ARE&M.NS": {"sector": "Industrials", "industry": "Electrical Equipment & Parts", "name": "AMARA RAJA ENERGY MOB LTD"}, "UNIONBANK.NS": {"sector": "Financial Services", "industry": "Banks - Regional", "name": "UNION BANK OF INDIA"}, "ITC.NS": {"sector": "Consumer Defensive", "industry": "Tobacco", "name": "ITC LTD"}, "BEL.NS": {"sector": "Industrials", "industry": "Aerospace & Defense", "name": "BHARAT ELECTRONICS LTD"}, "ABB.NS": {"sector": "Industrials", "industry": "Specialty Industrial Machinery", "name": "ABB INDIA LIMITED"}, "PRAJIND.NS": {"sector": "Industrials", "industry": "Engineering & Construction", "name": "PRAJ INDUSTRIES LTD"}, "CONCORDBIO.NS": {"sector": "Healthcare", "industry": "Biotechnology", "name": "CONCORD BIOTECH LIMITED"}, "MOTHERSON.NS": {"sector": "Consumer Cyclical", "industry": "Auto Parts", "name": "SAMVRDHNA MTHRSN INTL LTD"}, "COLPAL.NS": {"sector": "Consumer Defensive", "industry": "Household & Personal Products", "name": "COLGATE PALMOLIVE LTD."}, "TATACONSUM.NS": {"sector": "Consumer Defensive", "industry": "Packaged Foods", "name": "TATA CONSUMER PRODUCT LTD"}, "DABUR.NS": {"sector": "Consumer Defensive", "industry": "Household & Personal Products", "name": "DABUR INDIA LTD"}, "CEATLTD.NS": {"sector": "Consumer Cyclical", "industry": "Auto Parts", "name": "CEAT LIMITED"}, "MSUMI.NS": {"sector": "Consumer Cyclical", "industry": "Auto Parts", "name": "MOTHERSON SUMI WRNG IND L"}, "BALRAMCHIN.NS": {"sector": "Consumer Defensive", "industry": "Confectioners", "name": "BALRAMPUR CHINI MILLS LTD"}, "LICI.NS": {"sector": "Financial Services", "industry": "Insurance - Life", "name": "LIFE INSURA CORP OF INDIA"}, "MAHABANK.NS": {"sector": "Financial Services", "industry": "Banks - Regional", "name": "BANK OF MAHARASHTRA"}, "UCOBANK.NS": {"sector": "Financial Services", "industry": "Banks - Regional", "name": "UCO BANK"}, "NIVABUPA.NS": {"sector": "Financial Services", "industry": "Insurance - Life", "name": "NIVA BUPA HEALTH INS CO L"}, "ASHOKLEY.NS": {"sector": "Industrials", "industry": "Farm & Heavy Construction Machinery", "name": "ASHOK LEYLAND LTD"}, "AMBER.NS": {"sector": "Consumer Cyclical", "industry": "Furnishings, Fixtures & Appliances", "name": "AMBER ENTERPRISES (I) LTD"}, "TRITURBINE.NS": {"sector": "Industrials", "industry": "Specialty Industrial Machinery", "name": "TRIVENI TURBINE LIMITED"}, "ADANIPORTS.NS": {"sector": "Industrials", "industry": "Marine Shipping", "name": "ADANI PORT & SEZ LTD"}, "NTPCGREEN.NS": {"sector": "Utilities", "industry": "Utilities - Renewable", "name": "NTPC GREEN ENERGY LIMITED"}, "HAVELLS.NS": {"sector": "Industrials", "industry": "Electrical Equipment & Parts", "name": "HAVELLS INDIA LIMITED"}, "BAJAJHLDNG.NS": {"sector": "Financial Services", "industry": "Asset Management", "name": "BAJAJ HOLDINGS & INVS LTD"}, "AKZOINDIA.NS": {"sector": "Basic Materials", "industry": "Specialty Chemicals", "name": "AKZO NOBEL INDIA LIMITED"}, "LODHA.NS": {"sector": "Real Estate", "industry": "Real Estate - Development", "name": "LODHA DEVELOPERS LIMITED"}, "EXIDEIND.NS": {"sector": "Consumer Cyclical", "industry": "Auto Parts", "name": "EXIDE INDUSTRIES LTD"}, "MINDACORP.NS": {"sector": "Consumer Cyclical", "industry": "Auto Parts", "name": "MINDA CORPORATION LTD"}, "JMFINANCIL.NS": {"sector": "Financial Services", "industry": "Capital Markets", "name": "JM FINANCIAL LIMITED"}, "PAYTM.NS": {"sector": "Technology", "industry": "Software - Infrastructure", "name": "ONE 97 COMMUNICATIONS LTD"}, "MFSL.NS": {"sector": "Financial Services", "industry": "Insurance - Life", "name": "MAX FINANCIAL SERV LTD"}, "TATAINVEST.NS": {"sector": "Financial Services", "industry": "Capital Markets", "name": "TATA INVESTMENT CORP LTD"}, "HDFCBANK.NS": {"sector": "Financial Services", "industry": "Banks - Regional", "name": "HDFC BANK LTD"}, "ALKEM.NS": {"sector": "Healthcare", "industry": "Drug Manufacturers - Specialty & Generic", "name": "ALKEM LABORATORIES LTD."}, "TRIDENT.NS": {"sector": "Consumer Cyclical", "industry": "Textile Manufacturing", "name": "TRIDENT LIMITED"}, "MANYAVAR.NS": {"sector": "Consumer Cyclical", "industry": "Apparel Manufacturing", "name": "VEDANT FASHIONS LIMITED"}, "RKFORGE.NS": {"sector": "Industrials", "industry": "Metal Fabrication", "name": "RAMKRISHNA FORGINGS LTD"}, "GODIGIT.NS": {"sector": "Financial Services", "industry": "Insurance - Property & Casualty", "name": "GO DIGIT GENERAL INS LTD"}, "INDGN.NS": {"sector": "Healthcare", "industry": "Health Information Services", "name": "INDEGENE LIMITED"}, "ELGIEQUIP.NS": {"sector": "Industrials", "industry": "Specialty Industrial Machinery", "name": "ELGI EQUIPMENTS LTD"}, "PGHH.NS": {"sector": "Consumer Defensive", "industry": "Household & Personal Products", "name": "P&G HYGIENE & HEALTH CARE"}, "PNB.NS": {"sector": "Financial Services", "industry": "Banks - Regional", "name": "PUNJAB NATIONAL BANK"}, "JIOFIN.NS": {"sector": "Financial Services", "industry": "Asset Management", "name": "JIO FIN SERVICES LTD"}, "JSL.NS": {"sector": "Basic Materials", "industry": "Steel", "name": "JINDAL STAINLESS LIMITED"}, "CAMPUS.NS": {"sector": "Consumer Cyclical", "industry": "Footwear & Accessories", "name": "CAMPUS ACTIVEWEAR LIMITED"}, "IOC.NS": {"sector": "Energy", "industry": "Oil & Gas Refining & Marketing", "name": "INDIAN OIL CORP LTD"}, "ZEEL.NS": {"sector": "Communication Services", "industry": "Broadcasting", "name": "ZEE ENTERTAINMENT ENT LTD"}, "ASTRAL.NS": {"sector": "Industrials", "industry": "Building Products & Equipment", "name": "ASTRAL LIMITED"}, "TATATECH.NS": {"sector": "Technology", "industry": "Information Technology Services", "name": "TATA TECHNOLOGIES LIMITED"}, "LATENTVIEW.NS": {"sector": "Industrials", "industry": "Consulting Services", "name": "LATENT VIEW ANALYTICS LTD"}, "LTFOODS.NS": {"sector": "Consumer Defensive", "industry": "Packaged Foods", "name": "LT FOODS LIMITED"}, "TATASTEEL.NS": {"sector": "Basic Materials", "industry": "Steel", "name": "TATA STEEL LIMITED"}, "WELCORP.NS": {"sector": "Basic Materials", "industry": "Steel", "name": "WELSPUN CORP LIMITED"}, "ADANIPOWER.NS": {"sector": "Utilities", "industry": "Utilities - Independent Power Producers", "name": "ADANI POWER LTD"}, "JYOTICNC.NS": {"sector": "Industrials", "industry": "Specialty Industrial Machinery", "name": "JYOTI CNC AUTOMATION LTD"}, "SHYAMMETL.NS": {"sector": "Basic Materials", "industry": "Steel", "name": "SHYAM METALICS AND ENGY L"}, "SAPPHIRE.NS": {"sector": "Consumer Cyclical", "industry": "Restaurants", "name": "SAPPHIRE FOODS INDIA LTD"}, "AIIL.NS": {"sector": "Financial Services", "industry": "Capital Markets", "name": "AUTHUM INVEST & INFRA LTD"}, "SAILIFE.NS": {"sector": "Healthcare", "industry": "Diagnostics & Research", "name": "SAI LIFE SCIENCES LIMITED"}, "LTF.NS": {"sector": "Financial Services", "industry": "Credit Services", "name": "L&T FINANCE LIMITED"}, "ICICIBANK.NS": {"sector": "Financial Services", "industry": "Banks - Regional", "name": "ICICI BANK LTD."}, "JUBLFOOD.NS": {"sector": "Consumer Cyclical", "industry": "Restaurants", "name": "JUBILANT FOODWORKS LTD"}, "GMRAIRPORT.NS": {"sector": "Industrials", "industry": "Airports & Air Services", "name": "GMR AIRPORTS LIMITED"}, "KPITTECH.NS": {"sector": "Technology", "industry": "Software - Infrastructure", "name": "KPIT TECHNOLOGIES LIMITED"}, "ESCORTS.NS": {"sector": "Industrials", "industry": "Farm & Heavy Construction Machinery", "name": "ESCORTS KUBOTA LIMITED"}, "IDEA.NS": {"sector": "Communication Services", "industry": "Telecom Services", "name": "VODAFONE IDEA LIMITED"}, "ZYDUSLIFE.NS": {"sector": "Healthcare", "industry": "Drug Manufacturers - Specialty & Generic", "name": "ZYDUS LIFESCIENCES LTD"}, "PCBL.NS": {"sector": "Basic Materials", "industry": "Specialty Chemicals", "name": "PCBL CHEMICAL LIMITED"}, "IKS.NS": {"sector": "Healthcare", "industry": "Health Information Services", "name": "INVENTURUS KNOWLEDGE SO L"}, "MARUTI.NS": {"sector": "Consumer Cyclical", "industry": "Auto Manufacturers", "name": "MARUTI SUZUKI INDIA LTD."}, "WIPRO.NS": {"sector": "Technology", "industry": "Information Technology Services", "name": "WIPRO LTD"}, "AEGISLOG.NS": {"sector": "Energy", "industry": "Oil & Gas Refining & Marketing", "name": "AEGIS LOGISTICS LIMITED"}, "APARINDS.NS": {"sector": "Industrials", "industry": "Electrical Equipment & Parts", "name": "APAR INDUSTRIES LTD."}, "INDIAMART.NS": {"sector": "Communication Services", "industry": "Internet Content & Information", "name": "INDIAMART INTERMESH LTD"}, "NH.NS": {"sector": "Healthcare", "industry": "Medical Care Facilities", "name": "NARAYANA HRUDAYALAYA LTD."}, "ABSLAMC.NS": {"sector": "Financial Services", "industry": "Asset Management", "name": "ADIT BIRL SUN LIF AMC LTD"}, "BIOCON.NS": {"sector": "Healthcare", "industry": "Biotechnology", "name": "BIOCON LIMITED."}, "CRISIL.NS": {"sector": "Financial Services", "industry": "Financial Data & Stock Exchanges", "name": "CRISIL LTD"}, "APLLTD.NS": {"sector": "Healthcare", "industry": "Drug Manufacturers - Specialty & Generic", "name": "ALEMBIC PHARMA LTD"}, "VOLTAS.NS": {"sector": "Consumer Cyclical", "industry": "Furnishings, Fixtures & Appliances", "name": "VOLTAS LTD"}, "YESBANK.NS": {"sector": "Financial Services", "industry": "Banks - Regional", "name": "YES BANK LIMITED"}, "LLOYDSME.NS": {"sector": "Basic Materials", "industry": "Steel", "name": "LLOYDS METALS N ENERGY L"}, "LEMONTREE.NS": {"sector": "Consumer Cyclical", "industry": "Lodging", "name": "LEMON TREE HOTELS LTD"}, "BLUESTARCO.NS": {"sector": "Industrials", "industry": "Building Products & Equipment", "name": "BLUE STAR LIMITED"}, "BSE.NS": {"sector": "Financial Services", "industry": "Financial Data & Stock Exchanges", "name": "BSE LIMITED"}, "MRF.NS": {"sector": "Consumer Cyclical", "industry": "Auto Parts", "name": "MRF LTD"}, "ACE.NS": {"sector": "Industrials", "industry": "Farm & Heavy Construction Machinery", "name": "ACTION CONST EQUIP LTD"}, "KPIL.NS": {"sector": "Industrials", "industry": "Engineering & Construction", "name": "KALPATARU PROJECT INT LTD"}, "BAJAJFINSV.NS": {"sector": "Financial Services", "industry": "Financial Conglomerates", "name": "BAJAJ FINSERV LTD."}, "UTIAMC.NS": {"sector": "Financial Services", "industry": "Asset Management", "name": "UTI ASSET MNGMT CO LTD"}, "VGUARD.NS": {"sector": "Industrials", "industry": "Electrical Equipment & Parts", "name": "V-GUARD IND LTD."}, "MAXHEALTH.NS": {"sector": "Healthcare", "industry": "Medical Care Facilities", "name": "MAX HEALTHCARE INS LTD"}, "HINDPETRO.NS": {"sector": "Energy", "industry": "Oil & Gas Refining & Marketing", "name": "HINDUSTAN PETROLEUM CORP"}, "INDUSTOWER.NS": {"sector": "Communication Services", "industry": "Telecom Services", "name": "INDUS TOWERS LIMITED"}, "FINCABLES.NS": {"sector": "Industrials", "industry": "Electrical Equipment & Parts", "name": "FINOLEX CABLES LTD"}, "HCLTECH.NS": {"sector": "Technology", "industry": "Information Technology Services", "name": "HCL TECHNOLOGIES LTD"}, "NATCOPHARM.NS": {"sector": "Healthcare", "industry": "Drug Manufacturers - Specialty & Generic", "name": "NATCO PHARMA LTD."}, "J&KBANK.NS": {"sector": "Financial Services", "industry": "Banks - Regional", "name": "J & K BANK LTD."}, "AGARWALEYE.NS": {"sector": "Healthcare", "industry": "Medical Instruments & Supplies", "name": "DR AGARWALS HEALTH CARE L"}, "BHARTIARTL.NS": {"sector": "Communication Services", "industry": "Telecom Services", "name": "BHARTI AIRTEL LIMITED"}, "PERSISTENT.NS": {"sector": "Technology", "industry": "Information Technology Services", "name": "PERSISTENT SYSTEMS LTD"}, "DBREALTY.NS": {"sector": "Real Estate", "industry": "Real Estate - Development", "name": "VALOR ESTATE LIMITED"}, "SUNDRMFAST.NS": {"sector": "Consumer Cyclical", "industry": "Auto Parts", "name": "SUNDRAM FASTENERS LTD"}, "BHARATFORG.NS": {"sector": "Consumer Cyclical", "industry": "Auto Parts", "name": "BHARAT FORGE LTD"}, "MRPL.NS": {"sector": "Energy", "industry": "Oil & Gas Refining & Marketing", "name": "MRPL"}, "CGPOWER.NS": {"sector": "Industrials", "industry": "Electrical Equipment & Parts", "name": "CG POWER AND IND SOL LTD"}, "AARTIIND.NS": {"sector": "Basic Materials", "industry": "Specialty Chemicals", "name": "AARTI INDUSTRIES LTD"}, "TATAELXSI.NS": {"sector": "Technology", "industry": "Software - Application", "name": "TATA ELXSI LIMITED"}, "TEJASNET.NS": {"sector": "Technology", "industry": "Communication Equipment", "name": "TEJAS NETWORKS LIMITED"}, "KIRLOSBROS.NS": {"sector": "Industrials", "industry": "Specialty Industrial Machinery", "name": "KIRLOSKAR BROTHERS LTD"}, "CESC.NS": {"sector": "Utilities", "industry": "Utilities - Regulated Electric", "name": "CESC LTD"}, "HOMEFIRST.NS": {"sector": "Financial Services", "industry": "Mortgage Finance", "name": "HOME FIRST FIN CO IND LTD"}, "SKFINDIA.NS": {"sector": "Industrials", "industry": "Tools & Accessories", "name": "SKF INDIA LTD"}, "JKCEMENT.NS": {"sector": "Basic Materials", "industry": "Building Materials", "name": "JK CEMENT LIMITED"}, "ALKYLAMINE.NS": {"sector": "Basic Materials", "industry": "Specialty Chemicals", "name": "ALKYL AMINES CHEM. LTD"}, "BANDHANBNK.NS": {"sector": "Financial Services", "industry": "Banks - Regional", "name": "BANDHAN BANK LIMITED"}, "ERIS.NS": {"sector": "Healthcare", "industry": "Drug Manufacturers - Specialty & Generic", "name": "ERIS LIFESCIENCES LIMITED"}, "OLECTRA.NS": {"sector": "Industrials", "industry": "Farm & Heavy Construction Machinery", "name": "OLECTRA GREENTECH LIMITED"}, "CHALET.NS": {"sector": "Consumer Cyclical", "industry": "Lodging", "name": "CHALET HOTELS LIMITED"}, "HEROMOTOCO.NS": {"sector": "Consumer Cyclical", "industry": "Auto Manufacturers", "name": "HERO MOTOCORP LIMITED"}, "ABREL.NS": {"sector": "Real Estate", "industry": "Real Estate Services", "name": "ADITYA BIRLA REAL EST LTD"}, "RRKABEL.NS": {"sector": "Industrials", "industry": "Electrical Equipment & Parts", "name": "R R KABEL LIMITED"}, "HDFCLIFE.NS": {"sector": "Financial Services", "industry": "Insurance - Life", "name": "HDFC LIFE INS CO LTD"}, "TVSMOTOR.NS": {"sector": "Consumer Cyclical", "industry": "Auto Manufacturers", "name": "TVS MOTOR COMPANY  LTD"}, "RBLBANK.NS": {"sector": "Financial Services", "industry": "Banks - Regional", "name": "RBL BANK LIMITED"}, "POWERGRID.NS": {"sector": "Utilities", "industry": "Utilities - Regulated Electric", "name": "POWER GRID CORP. LTD."}, "CCL.NS": {"sector": "Consumer Defensive", "industry": "Packaged Foods", "name": "CCL PRODUCTS (I) LTD"}, "SUNPHARMA.NS": {"sector": "Healthcare", "industry": "Drug Manufacturers - Specialty & Generic", "name": "SUN PHARMACEUTICAL IND L"}, "PRESTIGE.NS": {"sector": "Real Estate", "industry": "Real Estate - Diversified", "name": "PRESTIGE ESTATE LTD"}, "ZENTEC.NS": {"sector": "Industrials", "industry": "Aerospace & Defense", "name": "ZEN TECHNOLOGIES LIMITED"}, "HAPPSTMNDS.NS": {"sector": "Technology", "industry": "Information Technology Services", "name": "HAPPIEST MINDS TECHNO LTD"}, "CENTURYPLY.NS": {"sector": "Basic Materials", "industry": "Lumber & Wood Production", "name": "CENTURY PLYBOARDS (I) LTD"}, "DIVISLAB.NS": {"sector": "Healthcare", "industry": "Drug Manufacturers - Specialty & Generic", "name": "DIVI S LABORATORIES LTD"}, "BOSCHLTD.NS": {"sector": "Consumer Cyclical", "industry": "Auto Parts", "name": "BOSCH LIMITED"}, "BANKBARODA.NS": {"sector": "Financial Services", "industry": "Banks - Regional", "name": "BANK OF BARODA"}, "SUNTV.NS": {"sector": "Communication Services", "industry": "Broadcasting", "name": "SUN TV NETWORK LIMITED"}, "ETERNAL.NS": {"sector": "Consumer Cyclical", "industry": "Internet Retail", "name": "ETERNAL LIMITED"}, "SAMMAANCAP.NS": {"sector": "Financial Services", "industry": "Mortgage Finance", "name": "SAMMAAN CAPITAL LIMITED"}, "NAM-INDIA.NS": {"sector": "Financial Services", "industry": "Asset Management", "name": "NIPPON L I A M LTD"}, "GLAXO.NS": {"sector": "Healthcare", "industry": "Drug Manufacturers - General", "name": "GLAXOSMITHKLINE PHARMA LT"}, "DCMSHRIRAM.NS": {"sector": "Industrials", "industry": "Conglomerates", "name": "DCM SHRIRAM LIMITED"}, "IIFL.NS": {"sector": "Financial Services", "industry": "Credit Services", "name": "IIFL FINANCE LIMITED"}, "FIVESTAR.NS": {"sector": "Financial Services", "industry": "Credit Services", "name": "FIVE-STAR BUS FIN LTD"}, "KEC.NS": {"sector": "Industrials", "industry": "Engineering & Construction", "name": "KEC INTL. LIMITED"}, "BAJAJ-AUTO.NS": {"sector": "Consumer Cyclical", "industry": "Auto Manufacturers", "name": "BAJAJ AUTO LIMITED"}, "SJVN.NS": {"sector": "Utilities", "industry": "Utilities - Renewable", "name": "SJVN LTD"}, "RAINBOW.NS": {"sector": "Healthcare", "industry": "Medical Care Facilities", "name": "RAINBOW CHILDRENS MED LTD"}, "TECHM.NS": {"sector": "Technology", "industry": "Information Technology Services", "name": "TECH MAHINDRA LIMITED"}, "BBTC.NS": {"sector": "Consumer Defensive", "industry": "Packaged Foods", "name": "BOMBAY BURMAH TRADING COR"}, "KAYNES.NS": {"sector": "Technology", "industry": "Electronic Components", "name": "KAYNES TECHNOLOGY IND LTD"}, "ANGELONE.NS": {"sector": "Financial Services", "industry": "Capital Markets", "name": "ANGEL ONE LIMITED"}, "BLS.NS": {"sector": "Industrials", "industry": "Specialty Business Services", "name": "BLS INTL SERVS LTD"}, "KEI.NS": {"sector": "Industrials", "industry": "Electrical Equipment & Parts", "name": "KEI INDUSTRIES LTD."}, "PREMIERENE.NS": {"sector": "Technology", "industry": "Solar", "name": "PREMIER ENERGIES LIMITED"}, "POLYCAB.NS": {"sector": "Industrials", "industry": "Electrical Equipment & Parts", "name": "POLYCAB INDIA LIMITED"}, "SCHNEIDER.NS": {"sector": "Industrials", "industry": "Electrical Equipment & Parts", "name": "SCHNEIDER ELECTRIC INFRA"}, "GESHIP.NS": {"sector": "Industrials", "industry": "Marine Shipping", "name": "THE GE SHPG.LTD"}, "MAPMYINDIA.NS": {"sector": "Technology", "industry": "Software - Infrastructure", "name": "C.E. INFO SYSTEMS LIMITED"}, "JSWENERGY.NS": {"sector": "Utilities", "industry": "Utilities - Independent Power Producers", "name": "JSW ENERGY LIMITED"}, "ENDURANCE.NS": {"sector": "Consumer Cyclical", "industry": "Auto Parts", "name": "ENDURANCE TECHNO. LTD."}, "TCS.NS": {"sector": "Technology", "industry": "Information Technology Services", "name": "TATA CONSULTANCY SERV LT"}, "BAJFINANCE.NS": {"sector": "Financial Services", "industry": "Credit Services", "name": "BAJAJ FINANCE LIMITED"}, "CDSL.NS": {"sector": "Financial Services", "industry": "Capital Markets", "name": "CENTRAL DEPO SER (I) LTD"}, "WAAREEENER.NS": {"sector": "Technology", "industry": "Solar", "name": "WAAREE ENERGIES LIMITED"}, "JINDALSTEL.NS": {"sector": "Basic Materials", "industry": "Steel", "name": "JINDAL STEEL LIMITED"}, "ABFRL.NS": {"sector": "Consumer Cyclical", "industry": "Apparel Manufacturing", "name": "ADITYA BIRLA FASHION & RT"}, "APOLLOTYRE.NS": {"sector": "Consumer Cyclical", "industry": "Auto Parts", "name": "APOLLO TYRES LTD"}, "COROMANDEL.NS": {"sector": "Basic Materials", "industry": "Agricultural Inputs", "name": "COROMANDEL INTERNTL. LTD"}, "360ONE.NS": {"sector": "Financial Services", "industry": "Asset Management", "name": "360 ONE WAM LIMITED"}, "NEWGEN.NS": {"sector": "Technology", "industry": "Software - Infrastructure", "name": "NEWGEN SOFTWARE TECH LTD"}, "SBFC.NS": {"sector": "Financial Services", "industry": "Credit Services", "name": "SBFC FINANCE LIMITED"}, "SHRIRAMFIN.NS": {"sector": "Financial Services", "industry": "Credit Services", "name": "SHRIRAM FINANCE LIMITED"}, "POLYMED.NS": {"sector": "Healthcare", "industry": "Medical Instruments & Supplies", "name": "POLY MEDICURE LIMITED"}, "ASIANPAINT.NS": {"sector": "Basic Materials", "industry": "Specialty Chemicals", "name": "ASIAN PAINTS LIMITED"}, "SUPREMEIND.NS": {"sector": "Industrials", "industry": "Building Products & Equipment", "name": "SUPREME INDUSTRIES LTD"}, "REDINGTON.NS": {"sector": "Technology", "industry": "Information Technology Services", "name": "REDINGTON LIMITED"}, "KSB.NS": {"sector": "Industrials", "industry": "Specialty Industrial Machinery", "name": "KSB LIMITED"}, "CAMS.NS": {"sector": "Technology", "industry": "Information Technology Services", "name": "COMPUTER AGE MNGT SER LTD"}, "NETWEB.NS": {"sector": "Technology", "industry": "Computer Hardware", "name": "NETWEB TECH INDIA LTD"}, "CUMMINSIND.NS": {"sector": "Industrials", "industry": "Specialty Industrial Machinery", "name": "CUMMINS INDIA LTD"}, "ASTRAZEN.NS": {"sector": "Healthcare", "industry": "Drug Manufacturers - Specialty & Generic", "name": "ASTRAZENECA PHARMA IND LT"}, "MPHASIS.NS": {"sector": "Technology", "industry": "Information Technology Services", "name": "MPHASIS LIMITED"}, "OIL.NS": {"sector": "Energy", "industry": "Oil & Gas Integrated", "name": "OIL INDIA LTD"}, "NAVA.NS": {"sector": "Industrials", "industry": "Conglomerates", "name": "NAVA LIMITED"}, "PPLPHARMA.NS": {"sector": "Healthcare", "industry": "Drug Manufacturers - Specialty & Generic", "name": "PIRAMAL PHARMA LIMITED"}, "CERA.NS": {"sector": "Industrials", "industry": "Building Products & Equipment", "name": "CERA SANITARYWARE LTD"}, "ATHERENERG.NS": {"sector": "Consumer Cyclical", "industry": "Auto Manufacturers", "name": "ATHER ENERGY LIMITED"}, "TECHNOE.NS": {"sector": "Industrials", "industry": "Engineering & Construction", "name": "TECHNO ELEC & ENG CO. LTD"}, "INOXINDIA.NS": {"sector": "Industrials", "industry": "Specialty Industrial Machinery", "name": "INOX INDIA LIMITED"}, "TTML.NS": {"sector": "Communication Services", "industry": "Telecom Services", "name": "TATA TELESERV(MAHARASTRA)"}, "CUB.NS": {"sector": "Financial Services", "industry": "Banks - Regional", "name": "CITY UNION BANK LTD"}, "BLUEJET.NS": {"sector": "Healthcare", "industry": "Biotechnology", "name": "BLUE JET HEALTHCARE LTD"}, "AIAENG.NS": {"sector": "Industrials", "industry": "Specialty Industrial Machinery", "name": "AIA ENGINEERING LIMITED"}, "UNOMINDA.NS": {"sector": "Consumer Cyclical", "industry": "Auto Parts", "name": "UNO MINDA LIMITED"}, "JSWINFRA.NS": {"sector": "Industrials", "industry": "Marine Shipping", "name": "JSW INFRASTRUCTURE LTD"}, "NCC.NS": {"sector": "Industrials", "industry": "Engineering & Construction", "name": "NCC LIMITED"}, "CLEAN.NS": {"sector": "Basic Materials", "industry": "Specialty Chemicals", "name": "CLEAN SCIENCE & TECH LTD"}, "NAVINFLUOR.NS": {"sector": "Basic Materials", "industry": "Chemicals", "name": "NAVIN FLUORINE INT. LTD"}, "MEDANTA.NS": {"sector": "Healthcare", "industry": "Medical Care Facilities", "name": "GLOBAL HEALTH LIMITED"}, "JPPOWER.NS": {"sector": "Utilities", "industry": "Utilities - Independent Power Producers", "name": "JAIPRAKASH POWER VEN. LTD"}, "WHIRLPOOL.NS": {"sector": "Consumer Cyclical", "industry": "Furnishings, Fixtures & Appliances", "name": "WHIRLPOOL OF INDIA LTD"}, "WELSPUNLIV.NS": {"sector": "Consumer Cyclical", "industry": "Textile Manufacturing", "name": "WELSPUN LIVING LIMITED"}, "ALOKINDS.NS": {"sector": "Consumer Cyclical", "industry": "Textile Manufacturing", "name": "ALOK INDUSTRIES LIMITED"}, "INTELLECT.NS": {"sector": "Technology", "industry": "Software - Application", "name": "INTELLECT DESIGN ARENA"}, "SWIGGY.NS": {"sector": "Consumer Cyclical", "industry": "Internet Retail", "name": "SWIGGY LIMITED"}, "BERGEPAINT.NS": {"sector": "Basic Materials", "industry": "Specialty Chemicals", "name": "BERGER PAINTS (I) LTD"}, "JKTYRE.NS": {"sector": "Consumer Cyclical", "industry": "Auto Parts", "name": "JK TYRE & INDUSTRIES LTD"}, "AAVAS.NS": {"sector": "Financial Services", "industry": "Mortgage Finance", "name": "AAVAS FINANCIERS LIMITED"}, "ZENSARTECH.NS": {"sector": "Technology", "industry": "Information Technology Services", "name": "ZENSAR TECHNOLOGIES  LTD"}, "TARIL.NS": {"sector": "Industrials", "industry": "Electrical Equipment & Parts", "name": "TRANS & RECTI. LTD"}, "LTTS.NS": {"sector": "Technology", "industry": "Information Technology Services", "name": "L&T TECHNOLOGY SER. LTD."}, "AJANTPHARM.NS": {"sector": "Healthcare", "industry": "Drug Manufacturers - Specialty & Generic", "name": "AJANTA PHARMA LIMITED"}, "CHENNPETRO.NS": {"sector": "Energy", "industry": "Oil & Gas Refining & Marketing", "name": "CHENNAI PETROLEUM CORP LT"}, "USHAMART.NS": {"sector": "Basic Materials", "industry": "Steel", "name": "USHA MARTIN LTD."}, "FSL.NS": {"sector": "Technology", "industry": "Information Technology Services", "name": "FIRSTSOURCE SOLU. LTD."}, "STARHEALTH.NS": {"sector": "Financial Services", "industry": "Insurance - Diversified", "name": "STAR HEALTH & AL INS CO L"}, "ECLERX.NS": {"sector": "Technology", "industry": "Information Technology Services", "name": "ECLERX SERVICES LTD"}, "CHOLAHLDNG.NS": {"sector": "Financial Services", "industry": "Credit Services", "name": "CHOLAMANDALAM FIN HOL LTD"}, "PVRINOX.NS": {"sector": "Communication Services", "industry": "Entertainment", "name": "PVR INOX LIMITED"}, "ANANTRAJ.NS": {"sector": "Real Estate", "industry": "Real Estate - Development", "name": "ANANT RAJ LIMITED"}, "NUVAMA.NS": {"sector": "Financial Services", "industry": "Asset Management", "name": "NUVAMA WEALTH MANAGE LTD"}, "LTIM.NS": {"sector": "Technology", "industry": "Information Technology Services", "name": "LTIMINDTREE LIMITED"}, "CANFINHOME.NS": {"sector": "Financial Services", "industry": "Mortgage Finance", "name": "CAN FIN HOMES LTD"}, "SARDAEN.NS": {"sector": "Basic Materials", "industry": "Steel", "name": "SARDA ENERGY & MIN LTD"}, "PNBHOUSING.NS": {"sector": "Financial Services", "industry": "Mortgage Finance", "name": "PNB HOUSING FIN LTD."}, "ACMESOLAR.NS": {"sector": "Utilities", "industry": "Utilities - Renewable", "name": "ACME SOLAR HOLDINGS LTD"}, "TIMKEN.NS": {"sector": "Industrials", "industry": "Tools & Accessories", "name": "TIMKEN INDIA LTD."}, "CREDITACC.NS": {"sector": "Financial Services", "industry": "Credit Services", "name": "CREDITACCESS GRAMEEN LTD"}, "IEX.NS": {"sector": "Financial Services", "industry": "Capital Markets", "name": "INDIAN ENERGY EXC LTD"}, "MOTILALOFS.NS": {"sector": "Financial Services", "industry": "Capital Markets", "name": "MOTILAL OSWAL FIN LTD"}, "DIXON.NS": {"sector": "Technology", "industry": "Consumer Electronics", "name": "DIXON TECHNO (INDIA) LTD"}, "HONASA.NS": {"sector": "Consumer Defensive", "industry": "Household & Personal Products", "name": "HONASA CONSUMER LIMITED"}, "GVT&D.NS": {"sector": "Industrials", "industry": "Specialty Industrial Machinery", "name": "GE VERNOVA T&D INDIA LTD"}, "CAPLIPOINT.NS": {"sector": "Healthcare", "industry": "Drug Manufacturers - Specialty & Generic", "name": "CAPLIN POINT LAB LTD."}, "HFCL.NS": {"sector": "Technology", "industry": "Communication Equipment", "name": "HFCL LIMITED"}, "COFORGE.NS": {"sector": "Technology", "industry": "Information Technology Services", "name": "COFORGE LIMITED"}, "FIRSTCRY.NS": {"sector": "Consumer Cyclical", "industry": "Internet Retail", "name": "BRAINBEES SOLUTIONS LTD"}, "JBMA.NS": {"sector": "Consumer Cyclical", "industry": "Auto Parts", "name": "JBM AUTO LIMITED"}, "RPOWER.NS": {"sector": "Utilities", "industry": "Utilities - Independent Power Producers", "name": "RELIANCE POWER LTD."}, "SURYAROSNI.NS": {"sector": "Basic Materials", "industry": "Steel", "name": "SURYA ROSHNI LTD"}}